redirects_cli/__init__.py
redirects_cli/__main__.py
redirects_cli/cli.py
redirects_cli-0.1.3.dist-info/entry_points.txt
redirects_cli-0.1.3.dist-info/LICENSE.md
redirects_cli-0.1.3.dist-info/WHEEL
redirects_cli-0.1.3.dist-info/METADATA
redirects_cli-0.1.3.dist-info/RECORD
