Metadata-Version: 2.1
Name: redirects_cli
Version: 0.1.3
Summary: Generates static redirections from a YAML file.
Home-page: https://github.com/dgarcia360/redirects_cli
Author: David Garcia
Author-email: hi@davidgarcia.dev
Requires-Python: >=3.7
Requires-Dist: typer >= 0.3
Requires-Dist: colorama >= 0.4
Requires-Dist: pre-commit ; extra == "test"
Requires-Dist: pytest ; extra == "test"
Provides-Extra: test
